loado/__init__.py
loado-5.8.1.dist-info/METADATA
loado-5.8.1.dist-info/WHEEL
loado-5.8.1.dist-info/top_level.txt
loado-5.8.1.dist-info/RECORD
