Metadata-Version: 2.1
Name: loado
Version: 5.8.1
Summary: Easy, modern, and beginner friendly loading animations.
Home-page: https://github.com/toolkitr/loado
Author: loado
Author-email: toolkitr.email@gmail.com
License: MIT
Classifier: License :: OSI Approved :: MIT License
Classifier: Programming Language :: Python :: 3
Classifier: Programming Language :: Python :: 3.7
Classifier: Topic :: Utilities
Classifier: Intended Audience :: Developers
Classifier: Development Status :: 5 - Production/Stable
Classifier: Development Status :: 4 - Beta
Classifier: Development Status :: 3 - Alpha
Classifier: Development Status :: 2 - Pre-Alpha
Classifier: Development Status :: 1 - Planning
Classifier: Operating System :: OS Independent
Classifier: Natural Language :: English
Requires-Python: >=3.7
